ipywidgets/__init__.py
ipywidgets/_version.py
ipywidgets/comm.py
ipywidgets/embed.py
ipywidgets/state.schema.json
ipywidgets/view.schema.json
ipywidgets/tests/__init__.py
ipywidgets/tests/test_embed.py
ipywidgets/widgets/__init__.py
ipywidgets/widgets/docutils.py
ipywidgets/widgets/domwidget.py
ipywidgets/widgets/interaction.py
ipywidgets/widgets/trait_types.py
ipywidgets/widgets/utils.py
ipywidgets/widgets/valuewidget.py
ipywidgets/widgets/widget.py
ipywidgets/widgets/widget_bool.py
ipywidgets/widgets/widget_box.py
ipywidgets/widgets/widget_button.py
ipywidgets/widgets/widget_color.py
ipywidgets/widgets/widget_controller.py
ipywidgets/widgets/widget_core.py
ipywidgets/widgets/widget_date.py
ipywidgets/widgets/widget_datetime.py
ipywidgets/widgets/widget_description.py
ipywidgets/widgets/widget_float.py
ipywidgets/widgets/widget_int.py
ipywidgets/widgets/widget_layout.py
ipywidgets/widgets/widget_link.py
ipywidgets/widgets/widget_media.py
ipywidgets/widgets/widget_output.py
ipywidgets/widgets/widget_selection.py
ipywidgets/widgets/widget_selectioncontainer.py
ipywidgets/widgets/widget_string.py
ipywidgets/widgets/widget_style.py
ipywidgets/widgets/widget_tagsinput.py
ipywidgets/widgets/widget_templates.py
ipywidgets/widgets/widget_time.py
ipywidgets/widgets/widget_upload.py
ipywidgets/widgets/tests/__init__.py
ipywidgets/widgets/tests/test_datetime_serializers.py
ipywidgets/widgets/tests/test_docutils.py
ipywidgets/widgets/tests/test_interaction.py
ipywidgets/widgets/tests/test_link.py
ipywidgets/widgets/tests/test_selectioncontainer.py
ipywidgets/widgets/tests/test_send_state.py
ipywidgets/widgets/tests/test_set_state.py
ipywidgets/widgets/tests/test_traits.py
ipywidgets/widgets/tests/test_utils.py
ipywidgets/widgets/tests/test_widget.py
ipywidgets/widgets/tests/test_widget_box.py
ipywidgets/widgets/tests/test_widget_button.py
ipywidgets/widgets/tests/test_widget_datetime.py
ipywidgets/widgets/tests/test_widget_float.py
ipywidgets-8.1.4.dist-info/LICENSE
ipywidgets-8.1.4.dist-info/METADATA
ipywidgets-8.1.4.dist-info/WHEEL
ipywidgets-8.1.4.dist-info/top_level.txt
ipywidgets-8.1.4.dist-info/RECORD
