Metadata-Version: 2.1
Name: ipywidgets
Version: 8.1.4
Summary: Jupyter interactive widgets
Home-page: http://jupyter.org
Author: Jupyter Development Team
Author-email: jupyter@googlegroups.com
License: BSD 3-Clause License
Keywords: Interactive,Interpreter,Shell,Web,ipython,widgets,Jupyter
Platform: Linux
Platform: Mac OS X
Platform: Windows
Classifier: Intended Audience :: Developers
Classifier: Intended Audience :: System Administrators
Classifier: Intended Audience :: Science/Research
Classifier: License :: OSI Approved :: BSD License
Classifier: Programming Language :: Python
Classifier: Programming Language :: Python :: 3
Classifier: Programming Language :: Python :: 3.7
Classifier: Programming Language :: Python :: 3.8
Classifier: Programming Language :: Python :: 3.9
Classifier: Programming Language :: Python :: 3.10
Classifier: Programming Language :: Python :: 3.11
Classifier: Programming Language :: Python :: 3 :: Only
Classifier: Framework :: Jupyter
Requires-Python: >=3.7
License-File: LICENSE
Requires-Dist: comm>=0.1.3
Requires-Dist: ipython>=6.1.0
Requires-Dist: traitlets>=4.3.1
Requires-Dist: widgetsnbextension~=4.0.12
Requires-Dist: jupyterlab-widgets~=3.0.12
Provides-Extra: test
Requires-Dist: jsonschema; extra == "test"
Requires-Dist: ipykernel; extra == "test"
Requires-Dist: pytest>=3.6.0; extra == "test"
Requires-Dist: pytest-cov; extra == "test"
Requires-Dist: pytz; extra == "test"
